envars/__init__.py
envars/envars.py
envars/kms.py
envars/models.py
envars/ssm.py
timeout_envars-0.3.dist-info/METADATA
timeout_envars-0.3.dist-info/WHEEL
timeout_envars-0.3.dist-info/entry_points.txt
timeout_envars-0.3.dist-info/top_level.txt
timeout_envars-0.3.dist-info/RECORD
