Metadata-Version: 2.1
Name: timeout-envars
Version: 0.3
Summary: A sample Python package
Author: Keith Harvey
Author-email: keith.harvey@timeout.com
Requires-Dist: argparse
Requires-Dist: pyyaml
Requires-Dist: boto3
Requires-Dist: jinja2
